[
  {
    "params": {
      "category": "company",
      "slug": "meta"
    },
    "lastUpdated": "2026-06-13T08:52:02.227Z",
    "count": 101
  },
  {
    "params": {
      "category": "company",
      "slug": "apple"
    },
    "lastUpdated": "2026-06-13T08:52:02.239Z",
    "count": 101
  },
  {
    "params": {
      "category": "company",
      "slug": "google"
    },
    "lastUpdated": "2026-06-13T08:52:02.286Z",
    "count": 100
  },
  {
    "params": {
      "category": "company",
      "slug": "samsung"
    },
    "lastUpdated": "2026-06-13T08:52:02.288Z",
    "count": 76
  },
  {
    "params": {
      "category": "company",
      "slug": "microsoft"
    },
    "lastUpdated": "2026-06-13T08:52:02.303Z",
    "count": 100
  },
  {
    "params": {
      "category": "company",
      "slug": "amazon"
    },
    "lastUpdated": "2026-06-13T08:52:02.305Z",
    "count": 100
  },
  {
    "params": {
      "category": "company",
      "slug": "tesla"
    },
    "lastUpdated": "2026-06-13T08:52:02.308Z",
    "count": 100
  }
]