[
  {
    "params": {
      "category": "company",
      "slug": "apple"
    },
    "lastUpdated": "2026-06-23T09:03:30.884Z",
    "count": 101
  },
  {
    "params": {
      "category": "company",
      "slug": "google"
    },
    "lastUpdated": "2026-06-23T09:03:30.890Z",
    "count": 101
  },
  {
    "params": {
      "category": "company",
      "slug": "tesla"
    },
    "lastUpdated": "2026-06-23T09:03:30.894Z",
    "count": 101
  },
  {
    "params": {
      "category": "company",
      "slug": "meta"
    },
    "lastUpdated": "2026-06-23T09:03:30.923Z",
    "count": 100
  },
  {
    "params": {
      "category": "company",
      "slug": "amazon"
    },
    "lastUpdated": "2026-06-23T09:03:30.930Z",
    "count": 100
  }
]