[
  {
    "params": {
      "category": "company",
      "slug": "apple"
    },
    "lastUpdated": "2026-05-05T01:57:05.293Z",
    "count": 102
  },
  {
    "params": {
      "category": "company",
      "slug": "amazon"
    },
    "lastUpdated": "2026-05-05T01:57:05.326Z",
    "count": 101
  },
  {
    "params": {
      "category": "company",
      "slug": "meta"
    },
    "lastUpdated": "2026-05-05T01:57:05.352Z",
    "count": 101
  },
  {
    "params": {
      "category": "company",
      "slug": "nvidia"
    },
    "lastUpdated": "2026-05-05T01:57:05.354Z",
    "count": 101
  }
]