[
  {
    "params": {
      "category": "company",
      "slug": "tesla"
    },
    "lastUpdated": "2025-12-31T18:21:59.270Z",
    "count": 44
  },
  {
    "params": {
      "category": "company",
      "slug": "microsoft"
    },
    "lastUpdated": "2025-12-31T18:21:59.274Z",
    "count": 39
  },
  {
    "params": {
      "category": "company",
      "slug": "apple"
    },
    "lastUpdated": "2025-12-31T18:21:59.283Z",
    "count": 50
  },
  {
    "params": {
      "category": "company",
      "slug": "meta"
    },
    "lastUpdated": "2025-12-31T18:21:59.285Z",
    "count": 58
  },
  {
    "params": {
      "category": "company",
      "slug": "google"
    },
    "lastUpdated": "2025-12-31T18:21:59.307Z",
    "count": 82
  },
  {
    "params": {
      "category": "company",
      "slug": "nvidia"
    },
    "lastUpdated": "2025-12-31T18:21:59.309Z",
    "count": 50
  },
  {
    "params": {
      "category": "company",
      "slug": "amazon"
    },
    "lastUpdated": "2025-12-31T18:21:59.321Z",
    "count": 44
  }
]