[
  {
    "params": {
      "category": "conflict",
      "slug": "war"
    },
    "lastUpdated": "2026-03-03T18:41:11.904Z",
    "count": 110
  },
  {
    "params": {
      "category": "conflict",
      "slug": "terrorism"
    },
    "lastUpdated": "2026-03-03T18:41:11.905Z",
    "count": 27
  },
  {
    "params": {
      "category": "conflict",
      "slug": "military"
    },
    "lastUpdated": "2026-03-03T18:41:11.912Z",
    "count": 103
  },
  {
    "params": {
      "category": "conflict",
      "slug": "air-force"
    },
    "lastUpdated": "2026-03-03T18:41:11.952Z",
    "count": 51
  },
  {
    "params": {
      "category": "conflict",
      "slug": "defense"
    },
    "lastUpdated": "2026-03-03T18:41:11.972Z",
    "count": 101
  },
  {
    "params": {
      "category": "conflict",
      "slug": "army"
    },
    "lastUpdated": "2026-03-03T18:41:12.034Z",
    "count": 66
  },
  {
    "params": {
      "category": "conflict",
      "slug": "navy"
    },
    "lastUpdated": "2026-03-03T18:41:12.083Z",
    "count": 77
  }
]