[
  {
    "params": {
      "category": "conflict",
      "slug": "defense"
    },
    "lastUpdated": "2026-04-07T13:01:22.654Z",
    "count": 102
  },
  {
    "params": {
      "category": "conflict",
      "slug": "war"
    },
    "lastUpdated": "2026-04-07T13:01:22.683Z",
    "count": 101
  },
  {
    "params": {
      "category": "conflict",
      "slug": "military"
    },
    "lastUpdated": "2026-04-07T13:01:22.692Z",
    "count": 101
  },
  {
    "params": {
      "category": "conflict",
      "slug": "air-force"
    },
    "lastUpdated": "2026-04-07T13:01:22.757Z",
    "count": 75
  },
  {
    "params": {
      "category": "conflict",
      "slug": "terrorism"
    },
    "lastUpdated": "2026-04-07T13:01:22.766Z",
    "count": 35
  }
]