[
  {
    "params": {
      "category": "conflict",
      "slug": "defense"
    },
    "lastUpdated": "2026-03-05T19:13:16.856Z",
    "count": 101
  },
  {
    "params": {
      "category": "conflict",
      "slug": "war"
    },
    "lastUpdated": "2026-03-05T19:13:16.903Z",
    "count": 106
  },
  {
    "params": {
      "category": "conflict",
      "slug": "military"
    },
    "lastUpdated": "2026-03-05T19:13:16.984Z",
    "count": 100
  },
  {
    "params": {
      "category": "conflict",
      "slug": "terrorism"
    },
    "lastUpdated": "2026-03-05T19:13:17.031Z",
    "count": 28
  }
]