[
  {
    "params": {
      "category": "conflict",
      "slug": "war"
    },
    "lastUpdated": "2026-03-08T12:31:03.475Z",
    "count": 106
  },
  {
    "params": {
      "category": "conflict",
      "slug": "military"
    },
    "lastUpdated": "2026-03-08T12:31:03.478Z",
    "count": 103
  },
  {
    "params": {
      "category": "conflict",
      "slug": "air-force"
    },
    "lastUpdated": "2026-03-08T12:31:03.499Z",
    "count": 56
  },
  {
    "params": {
      "category": "conflict",
      "slug": "defense"
    },
    "lastUpdated": "2026-03-08T12:31:03.581Z",
    "count": 100
  },
  {
    "params": {
      "category": "conflict",
      "slug": "terrorism"
    },
    "lastUpdated": "2026-03-08T12:31:03.596Z",
    "count": 30
  }
]