[
  {
    "params": {
      "category": "conflict",
      "slug": "air-force"
    },
    "lastUpdated": "2025-12-18T06:23:23.456Z",
    "count": 8
  },
  {
    "params": {
      "category": "conflict",
      "slug": "defense"
    },
    "lastUpdated": "2025-12-18T06:23:23.458Z",
    "count": 26
  },
  {
    "params": {
      "category": "conflict",
      "slug": "military"
    },
    "lastUpdated": "2025-12-18T06:23:23.479Z",
    "count": 33
  },
  {
    "params": {
      "category": "conflict",
      "slug": "war"
    },
    "lastUpdated": "2025-12-18T06:23:23.483Z",
    "count": 54
  },
  {
    "params": {
      "category": "conflict",
      "slug": "navy"
    },
    "lastUpdated": "2025-12-18T06:23:23.489Z",
    "count": 13
  }
]