[
  {
    "params": {
      "category": "conflict",
      "slug": "defense"
    },
    "lastUpdated": "2026-06-26T14:07:43.427Z",
    "count": 102
  },
  {
    "params": {
      "category": "conflict",
      "slug": "army"
    },
    "lastUpdated": "2026-06-26T14:07:43.743Z",
    "count": 101
  },
  {
    "params": {
      "category": "conflict",
      "slug": "war"
    },
    "lastUpdated": "2026-06-26T14:07:43.777Z",
    "count": 101
  },
  {
    "params": {
      "category": "conflict",
      "slug": "military"
    },
    "lastUpdated": "2026-06-26T14:07:43.789Z",
    "count": 100
  }
]