[
  {
    "params": {
      "category": "demographic",
      "slug": "student"
    },
    "lastUpdated": "2026-02-05T06:49:03.112Z",
    "count": 79
  },
  {
    "params": {
      "category": "demographic",
      "slug": "founder"
    },
    "lastUpdated": "2026-02-05T06:49:03.180Z",
    "count": 100
  },
  {
    "params": {
      "category": "demographic",
      "slug": "investor"
    },
    "lastUpdated": "2026-02-05T06:49:03.218Z",
    "count": 98
  },
  {
    "params": {
      "category": "demographic",
      "slug": "veteran"
    },
    "lastUpdated": "2026-02-05T06:49:03.230Z",
    "count": 100
  }
]