[
  {
    "params": {
      "category": "event",
      "slug": "olympics"
    },
    "lastUpdated": "2026-02-06T12:40:24.826Z",
    "count": 94
  },
  {
    "params": {
      "category": "event",
      "slug": "world-cup"
    },
    "lastUpdated": "2026-02-06T12:40:24.839Z",
    "count": 108
  },
  {
    "params": {
      "category": "event",
      "slug": "super-bowl"
    },
    "lastUpdated": "2026-02-06T12:40:24.861Z",
    "count": 104
  },
  {
    "params": {
      "category": "event",
      "slug": "election"
    },
    "lastUpdated": "2026-02-06T12:40:24.951Z",
    "count": 100
  }
]