[
  {
    "params": {
      "category": "government",
      "slug": "sec"
    },
    "lastUpdated": "2026-03-05T19:13:16.876Z",
    "count": 26
  },
  {
    "params": {
      "category": "government",
      "slug": "fbi"
    },
    "lastUpdated": "2026-03-05T19:13:16.918Z",
    "count": 40
  },
  {
    "params": {
      "category": "government",
      "slug": "dhs"
    },
    "lastUpdated": "2026-03-05T19:13:16.921Z",
    "count": 64
  },
  {
    "params": {
      "category": "government",
      "slug": "pentagon"
    },
    "lastUpdated": "2026-03-05T19:13:16.963Z",
    "count": 83
  },
  {
    "params": {
      "category": "government",
      "slug": "state-department"
    },
    "lastUpdated": "2026-03-05T19:13:17.020Z",
    "count": 11
  }
]