[
  {
    "params": {
      "category": "industry",
      "slug": "manufacturing"
    },
    "lastUpdated": "2026-06-14T13:31:52.158Z",
    "count": 101
  },
  {
    "params": {
      "category": "industry",
      "slug": "healthcare"
    },
    "lastUpdated": "2026-06-14T13:31:52.166Z",
    "count": 101
  },
  {
    "params": {
      "category": "industry",
      "slug": "energy"
    },
    "lastUpdated": "2026-06-14T13:31:52.170Z",
    "count": 102
  },
  {
    "params": {
      "category": "industry",
      "slug": "real-estate"
    },
    "lastUpdated": "2026-06-14T13:31:52.200Z",
    "count": 101
  },
  {
    "params": {
      "category": "industry",
      "slug": "technology"
    },
    "lastUpdated": "2026-06-14T13:31:52.203Z",
    "count": 101
  },
  {
    "params": {
      "category": "industry",
      "slug": "automotive"
    },
    "lastUpdated": "2026-06-14T13:31:52.249Z",
    "count": 100
  },
  {
    "params": {
      "category": "industry",
      "slug": "construction"
    },
    "lastUpdated": "2026-06-14T13:31:52.273Z",
    "count": 100
  },
  {
    "params": {
      "category": "industry",
      "slug": "banking"
    },
    "lastUpdated": "2026-06-14T13:31:52.274Z",
    "count": 100
  }
]