[
  {
    "params": {
      "category": "industry",
      "slug": "banking"
    },
    "lastUpdated": "2026-04-15T19:04:48.320Z",
    "count": 101
  },
  {
    "params": {
      "category": "industry",
      "slug": "retail"
    },
    "lastUpdated": "2026-04-15T19:04:48.332Z",
    "count": 88
  },
  {
    "params": {
      "category": "industry",
      "slug": "energy"
    },
    "lastUpdated": "2026-04-15T19:04:48.359Z",
    "count": 101
  },
  {
    "params": {
      "category": "industry",
      "slug": "real-estate"
    },
    "lastUpdated": "2026-04-15T19:04:48.375Z",
    "count": 92
  },
  {
    "params": {
      "category": "industry",
      "slug": "technology"
    },
    "lastUpdated": "2026-04-15T19:04:48.396Z",
    "count": 100
  }
]