[
  {
    "params": {
      "category": "industry",
      "slug": "banking"
    },
    "lastUpdated": "2026-01-04T18:22:25.155Z",
    "count": 96
  },
  {
    "params": {
      "category": "industry",
      "slug": "technology"
    },
    "lastUpdated": "2026-01-04T18:22:25.183Z",
    "count": 101
  },
  {
    "params": {
      "category": "industry",
      "slug": "automotive"
    },
    "lastUpdated": "2026-01-04T18:22:25.185Z",
    "count": 45
  },
  {
    "params": {
      "category": "industry",
      "slug": "energy"
    },
    "lastUpdated": "2026-01-04T18:22:25.187Z",
    "count": 102
  },
  {
    "params": {
      "category": "industry",
      "slug": "healthcare"
    },
    "lastUpdated": "2026-01-04T18:22:25.189Z",
    "count": 20
  },
  {
    "params": {
      "category": "industry",
      "slug": "retail"
    },
    "lastUpdated": "2026-01-04T18:22:25.213Z",
    "count": 21
  },
  {
    "params": {
      "category": "industry",
      "slug": "manufacturing"
    },
    "lastUpdated": "2026-01-04T18:22:25.241Z",
    "count": 27
  }
]