[
  {
    "params": {
      "category": "industry",
      "slug": "energy"
    },
    "lastUpdated": "2026-05-04T13:26:38.132Z",
    "count": 104
  },
  {
    "params": {
      "category": "industry",
      "slug": "banking"
    },
    "lastUpdated": "2026-05-04T13:26:38.154Z",
    "count": 103
  },
  {
    "params": {
      "category": "industry",
      "slug": "healthcare"
    },
    "lastUpdated": "2026-05-04T13:26:38.210Z",
    "count": 101
  },
  {
    "params": {
      "category": "industry",
      "slug": "automotive"
    },
    "lastUpdated": "2026-05-04T13:26:38.225Z",
    "count": 100
  },
  {
    "params": {
      "category": "industry",
      "slug": "manufacturing"
    },
    "lastUpdated": "2026-05-04T13:26:38.243Z",
    "count": 100
  },
  {
    "params": {
      "category": "industry",
      "slug": "technology"
    },
    "lastUpdated": "2026-05-04T13:26:38.262Z",
    "count": 100
  }
]