[
  {
    "params": {
      "category": "industry",
      "slug": "real-estate"
    },
    "lastUpdated": "2026-04-19T07:11:09.977Z",
    "count": 95
  },
  {
    "params": {
      "category": "industry",
      "slug": "construction"
    },
    "lastUpdated": "2026-04-19T07:11:09.983Z",
    "count": 64
  },
  {
    "params": {
      "category": "industry",
      "slug": "manufacturing"
    },
    "lastUpdated": "2026-04-19T07:11:09.988Z",
    "count": 101
  },
  {
    "params": {
      "category": "industry",
      "slug": "energy"
    },
    "lastUpdated": "2026-04-19T07:11:10.019Z",
    "count": 100
  }
]