[
  {
    "params": {
      "category": "industry",
      "slug": "technology"
    },
    "lastUpdated": "2025-12-19T09:44:04.307Z",
    "count": 55
  },
  {
    "params": {
      "category": "industry",
      "slug": "banking"
    },
    "lastUpdated": "2025-12-19T09:44:04.308Z",
    "count": 45
  },
  {
    "params": {
      "category": "industry",
      "slug": "automotive"
    },
    "lastUpdated": "2025-12-19T09:44:04.309Z",
    "count": 25
  },
  {
    "params": {
      "category": "industry",
      "slug": "energy"
    },
    "lastUpdated": "2025-12-19T09:44:04.311Z",
    "count": 85
  },
  {
    "params": {
      "category": "industry",
      "slug": "healthcare"
    },
    "lastUpdated": "2025-12-19T09:44:04.313Z",
    "count": 6
  },
  {
    "params": {
      "category": "industry",
      "slug": "manufacturing"
    },
    "lastUpdated": "2025-12-19T09:44:04.316Z",
    "count": 8
  }
]