[
  {
    "params": {
      "category": "interest",
      "slug": "ai"
    },
    "lastUpdated": "2026-01-10T06:22:05.753Z",
    "count": 104
  },
  {
    "params": {
      "category": "interest",
      "slug": "fashion"
    },
    "lastUpdated": "2026-01-10T06:22:05.768Z",
    "count": 88
  },
  {
    "params": {
      "category": "interest",
      "slug": "gaming"
    },
    "lastUpdated": "2026-01-10T06:22:05.814Z",
    "count": 80
  },
  {
    "params": {
      "category": "interest",
      "slug": "travel"
    },
    "lastUpdated": "2026-01-10T06:22:05.817Z",
    "count": 100
  },
  {
    "params": {
      "category": "interest",
      "slug": "fitness"
    },
    "lastUpdated": "2026-01-10T06:22:05.818Z",
    "count": 31
  }
]