[
  {
    "params": {
      "category": "interest",
      "slug": "fashion"
    },
    "lastUpdated": "2026-02-09T01:17:37.529Z",
    "count": 101
  },
  {
    "params": {
      "category": "interest",
      "slug": "ai"
    },
    "lastUpdated": "2026-02-09T01:17:37.554Z",
    "count": 104
  },
  {
    "params": {
      "category": "interest",
      "slug": "coding"
    },
    "lastUpdated": "2026-02-09T01:17:37.563Z",
    "count": 101
  },
  {
    "params": {
      "category": "interest",
      "slug": "crypto"
    },
    "lastUpdated": "2026-02-09T01:17:37.565Z",
    "count": 101
  }
]