[
  {
    "params": {
      "category": "interest",
      "slug": "ai"
    },
    "lastUpdated": "2026-02-26T12:44:26.909Z",
    "count": 116
  },
  {
    "params": {
      "category": "interest",
      "slug": "fashion"
    },
    "lastUpdated": "2026-02-26T12:44:26.944Z",
    "count": 101
  },
  {
    "params": {
      "category": "interest",
      "slug": "coding"
    },
    "lastUpdated": "2026-02-26T12:44:26.993Z",
    "count": 100
  },
  {
    "params": {
      "category": "interest",
      "slug": "travel"
    },
    "lastUpdated": "2026-02-26T12:44:27.014Z",
    "count": 100
  },
  {
    "params": {
      "category": "interest",
      "slug": "photography"
    },
    "lastUpdated": "2026-02-26T12:44:27.034Z",
    "count": 13
  }
]