[
  {
    "params": {
      "category": "interest",
      "slug": "ai"
    },
    "lastUpdated": "2026-02-03T12:40:01.144Z",
    "count": 113
  },
  {
    "params": {
      "category": "interest",
      "slug": "writing"
    },
    "lastUpdated": "2026-02-03T12:40:01.177Z",
    "count": 72
  },
  {
    "params": {
      "category": "interest",
      "slug": "travel"
    },
    "lastUpdated": "2026-02-03T12:40:01.180Z",
    "count": 101
  },
  {
    "params": {
      "category": "interest",
      "slug": "fashion"
    },
    "lastUpdated": "2026-02-03T12:40:01.183Z",
    "count": 101
  },
  {
    "params": {
      "category": "interest",
      "slug": "fitness"
    },
    "lastUpdated": "2026-02-03T12:40:01.188Z",
    "count": 66
  },
  {
    "params": {
      "category": "interest",
      "slug": "coding"
    },
    "lastUpdated": "2026-02-03T12:40:01.239Z",
    "count": 100
  }
]