[
  {
    "params": {
      "category": "interest",
      "slug": "ai"
    },
    "lastUpdated": "2026-02-17T18:47:35.373Z",
    "count": 115
  },
  {
    "params": {
      "category": "interest",
      "slug": "coding"
    },
    "lastUpdated": "2026-02-17T18:47:35.376Z",
    "count": 101
  },
  {
    "params": {
      "category": "interest",
      "slug": "cooking"
    },
    "lastUpdated": "2026-02-17T18:47:35.404Z",
    "count": 104
  },
  {
    "params": {
      "category": "interest",
      "slug": "fashion"
    },
    "lastUpdated": "2026-02-17T18:47:35.438Z",
    "count": 101
  },
  {
    "params": {
      "category": "interest",
      "slug": "travel"
    },
    "lastUpdated": "2026-02-17T18:47:35.485Z",
    "count": 100
  },
  {
    "params": {
      "category": "interest",
      "slug": "crypto"
    },
    "lastUpdated": "2026-02-17T18:47:35.525Z",
    "count": 100
  },
  {
    "params": {
      "category": "interest",
      "slug": "fitness"
    },
    "lastUpdated": "2026-02-17T18:47:35.533Z",
    "count": 88
  }
]