[
  {
    "params": {
      "category": "interest",
      "slug": "fitness"
    },
    "lastUpdated": "2025-12-28T18:21:31.149Z",
    "count": 19
  },
  {
    "params": {
      "category": "interest",
      "slug": "ai"
    },
    "lastUpdated": "2025-12-28T18:21:31.155Z",
    "count": 104
  },
  {
    "params": {
      "category": "interest",
      "slug": "writing"
    },
    "lastUpdated": "2025-12-28T18:21:31.159Z",
    "count": 28
  },
  {
    "params": {
      "category": "interest",
      "slug": "travel"
    },
    "lastUpdated": "2025-12-28T18:21:31.174Z",
    "count": 59
  },
  {
    "params": {
      "category": "interest",
      "slug": "cooking"
    },
    "lastUpdated": "2025-12-28T18:21:31.184Z",
    "count": 49
  },
  {
    "params": {
      "category": "interest",
      "slug": "fashion"
    },
    "lastUpdated": "2025-12-28T18:21:31.231Z",
    "count": 46
  },
  {
    "params": {
      "category": "interest",
      "slug": "coding"
    },
    "lastUpdated": "2025-12-28T18:21:31.239Z",
    "count": 34
  },
  {
    "params": {
      "category": "interest",
      "slug": "crypto"
    },
    "lastUpdated": "2025-12-28T18:21:31.241Z",
    "count": 62
  }
]