[
  {
    "params": {
      "category": "interest",
      "slug": "travel"
    },
    "lastUpdated": "2026-03-20T12:39:28.445Z",
    "count": 102
  },
  {
    "params": {
      "category": "interest",
      "slug": "ai"
    },
    "lastUpdated": "2026-03-20T12:39:28.458Z",
    "count": 112
  },
  {
    "params": {
      "category": "interest",
      "slug": "fashion"
    },
    "lastUpdated": "2026-03-20T12:39:28.461Z",
    "count": 101
  },
  {
    "params": {
      "category": "interest",
      "slug": "cooking"
    },
    "lastUpdated": "2026-03-20T12:39:28.493Z",
    "count": 101
  },
  {
    "params": {
      "category": "interest",
      "slug": "coding"
    },
    "lastUpdated": "2026-03-20T12:39:28.514Z",
    "count": 101
  },
  {
    "params": {
      "category": "interest",
      "slug": "gaming"
    },
    "lastUpdated": "2026-03-20T12:39:28.540Z",
    "count": 101
  },
  {
    "params": {
      "category": "interest",
      "slug": "writing"
    },
    "lastUpdated": "2026-03-20T12:39:28.543Z",
    "count": 101
  },
  {
    "params": {
      "category": "interest",
      "slug": "crypto"
    },
    "lastUpdated": "2026-03-20T12:39:28.579Z",
    "count": 100
  }
]