[
  {
    "params": {
      "category": "keywords",
      "slug": "immigration"
    },
    "lastUpdated": "2026-01-27T18:29:19.483Z",
    "count": 104
  },
  {
    "params": {
      "category": "keywords",
      "slug": "layoffs"
    },
    "lastUpdated": "2026-01-27T18:29:19.542Z",
    "count": 7
  },
  {
    "params": {
      "category": "keywords",
      "slug": "inflation"
    },
    "lastUpdated": "2026-01-27T18:29:19.607Z",
    "count": 73
  },
  {
    "params": {
      "category": "keywords",
      "slug": "interest-rates"
    },
    "lastUpdated": "2026-01-27T18:29:19.611Z",
    "count": 59
  }
]