[
  {
    "params": {
      "category": "legal",
      "slug": "crime"
    },
    "lastUpdated": "2026-04-23T13:04:47.496Z",
    "count": 100
  },
  {
    "params": {
      "category": "legal",
      "slug": "supreme-court"
    },
    "lastUpdated": "2026-04-23T13:04:47.508Z",
    "count": 100
  },
  {
    "params": {
      "category": "legal",
      "slug": "lawsuit"
    },
    "lastUpdated": "2026-04-23T13:04:47.510Z",
    "count": 100
  },
  {
    "params": {
      "category": "legal",
      "slug": "judge"
    },
    "lastUpdated": "2026-04-23T13:04:47.514Z",
    "count": 100
  }
]