[
  {
    "params": {
      "category": "legal",
      "slug": "crime"
    },
    "lastUpdated": "2026-03-12T12:39:49.451Z",
    "count": 89
  },
  {
    "params": {
      "category": "legal",
      "slug": "regulation"
    },
    "lastUpdated": "2026-03-12T12:39:49.466Z",
    "count": 60
  },
  {
    "params": {
      "category": "legal",
      "slug": "lawsuit"
    },
    "lastUpdated": "2026-03-12T12:39:49.516Z",
    "count": 100
  },
  {
    "params": {
      "category": "legal",
      "slug": "judge"
    },
    "lastUpdated": "2026-03-12T12:39:49.533Z",
    "count": 100
  }
]