[
  {
    "params": {
      "category": "location",
      "slug": "florida"
    },
    "lastUpdated": "2025-12-18T06:23:23.457Z",
    "count": 28
  },
  {
    "params": {
      "category": "location",
      "slug": "london"
    },
    "lastUpdated": "2025-12-18T06:23:23.462Z",
    "count": 16
  },
  {
    "params": {
      "category": "location",
      "slug": "texas"
    },
    "lastUpdated": "2025-12-18T06:23:23.466Z",
    "count": 39
  },
  {
    "params": {
      "category": "location",
      "slug": "china"
    },
    "lastUpdated": "2025-12-18T06:23:23.471Z",
    "count": 79
  },
  {
    "params": {
      "category": "location",
      "slug": "new-york"
    },
    "lastUpdated": "2025-12-18T06:23:23.475Z",
    "count": 69
  },
  {
    "params": {
      "category": "location",
      "slug": "beijing"
    },
    "lastUpdated": "2025-12-18T06:23:23.480Z",
    "count": 7
  },
  {
    "params": {
      "category": "location",
      "slug": "ukraine"
    },
    "lastUpdated": "2025-12-18T06:23:23.487Z",
    "count": 47
  },
  {
    "params": {
      "category": "location",
      "slug": "washington"
    },
    "lastUpdated": "2025-12-18T06:23:23.489Z",
    "count": 26
  },
  {
    "params": {
      "category": "location",
      "slug": "california"
    },
    "lastUpdated": "2025-12-18T06:23:23.494Z",
    "count": 31
  },
  {
    "params": {
      "category": "location",
      "slug": "russia"
    },
    "lastUpdated": "2025-12-18T06:23:23.506Z",
    "count": 40
  }
]