[
  {
    "params": {
      "category": "location",
      "slug": "new-york"
    },
    "lastUpdated": "2026-01-17T18:21:09.253Z",
    "count": 101
  },
  {
    "params": {
      "category": "location",
      "slug": "washington"
    },
    "lastUpdated": "2026-01-17T18:21:09.256Z",
    "count": 104
  },
  {
    "params": {
      "category": "location",
      "slug": "paris"
    },
    "lastUpdated": "2026-01-17T18:21:09.268Z",
    "count": 25
  },
  {
    "params": {
      "category": "location",
      "slug": "california"
    },
    "lastUpdated": "2026-01-17T18:21:09.279Z",
    "count": 102
  },
  {
    "params": {
      "category": "location",
      "slug": "london"
    },
    "lastUpdated": "2026-01-17T18:21:09.284Z",
    "count": 76
  },
  {
    "params": {
      "category": "location",
      "slug": "texas"
    },
    "lastUpdated": "2026-01-17T18:21:09.334Z",
    "count": 101
  },
  {
    "params": {
      "category": "location",
      "slug": "florida"
    },
    "lastUpdated": "2026-01-17T18:21:09.337Z",
    "count": 100
  },
  {
    "params": {
      "category": "location",
      "slug": "china"
    },
    "lastUpdated": "2026-01-17T18:21:09.339Z",
    "count": 101
  },
  {
    "params": {
      "category": "location",
      "slug": "israel"
    },
    "lastUpdated": "2026-01-17T18:21:09.347Z",
    "count": 36
  },
  {
    "params": {
      "category": "location",
      "slug": "gaza"
    },
    "lastUpdated": "2026-01-17T18:21:09.348Z",
    "count": 7
  },
  {
    "params": {
      "category": "location",
      "slug": "india"
    },
    "lastUpdated": "2026-01-17T18:21:09.355Z",
    "count": 75
  },
  {
    "params": {
      "category": "location",
      "slug": "ukraine"
    },
    "lastUpdated": "2026-01-17T18:21:09.374Z",
    "count": 100
  },
  {
    "params": {
      "category": "location",
      "slug": "russia"
    },
    "lastUpdated": "2026-01-17T18:21:09.399Z",
    "count": 100
  },
  {
    "params": {
      "category": "location",
      "slug": "kyiv"
    },
    "lastUpdated": "2026-01-17T18:21:09.402Z",
    "count": 6
  }
]