[
  {
    "params": {
      "category": "location",
      "slug": "new-york"
    },
    "lastUpdated": "2026-05-22T08:52:38.826Z",
    "count": 102
  },
  {
    "params": {
      "category": "location",
      "slug": "london"
    },
    "lastUpdated": "2026-05-22T08:52:38.847Z",
    "count": 101
  },
  {
    "params": {
      "category": "location",
      "slug": "china"
    },
    "lastUpdated": "2026-05-22T08:52:38.862Z",
    "count": 101
  },
  {
    "params": {
      "category": "location",
      "slug": "texas"
    },
    "lastUpdated": "2026-05-22T08:52:38.873Z",
    "count": 101
  },
  {
    "params": {
      "category": "location",
      "slug": "ukraine"
    },
    "lastUpdated": "2026-05-22T08:52:38.886Z",
    "count": 101
  },
  {
    "params": {
      "category": "location",
      "slug": "russia"
    },
    "lastUpdated": "2026-05-22T08:52:38.896Z",
    "count": 101
  },
  {
    "params": {
      "category": "location",
      "slug": "california"
    },
    "lastUpdated": "2026-05-22T08:52:38.957Z",
    "count": 100
  }
]