[
  {
    "params": {
      "category": "location",
      "slug": "paris"
    },
    "lastUpdated": "2026-02-10T01:26:32.449Z",
    "count": 58
  },
  {
    "params": {
      "category": "location",
      "slug": "california"
    },
    "lastUpdated": "2026-02-10T01:26:32.460Z",
    "count": 103
  },
  {
    "params": {
      "category": "location",
      "slug": "texas"
    },
    "lastUpdated": "2026-02-10T01:26:32.492Z",
    "count": 102
  },
  {
    "params": {
      "category": "location",
      "slug": "india"
    },
    "lastUpdated": "2026-02-10T01:26:32.501Z",
    "count": 101
  },
  {
    "params": {
      "category": "location",
      "slug": "london"
    },
    "lastUpdated": "2026-02-10T01:26:32.507Z",
    "count": 101
  }
]