[
  {
    "params": {
      "category": "location",
      "slug": "london"
    },
    "lastUpdated": "2026-02-04T18:39:37.316Z",
    "count": 102
  },
  {
    "params": {
      "category": "location",
      "slug": "new-york"
    },
    "lastUpdated": "2026-02-04T18:39:37.541Z",
    "count": 102
  },
  {
    "params": {
      "category": "location",
      "slug": "washington"
    },
    "lastUpdated": "2026-02-04T18:39:37.562Z",
    "count": 104
  },
  {
    "params": {
      "category": "location",
      "slug": "russia"
    },
    "lastUpdated": "2026-02-04T18:39:37.612Z",
    "count": 104
  },
  {
    "params": {
      "category": "location",
      "slug": "ukraine"
    },
    "lastUpdated": "2026-02-04T18:39:37.616Z",
    "count": 104
  },
  {
    "params": {
      "category": "location",
      "slug": "california"
    },
    "lastUpdated": "2026-02-04T18:39:37.623Z",
    "count": 103
  },
  {
    "params": {
      "category": "location",
      "slug": "israel"
    },
    "lastUpdated": "2026-02-04T18:39:37.625Z",
    "count": 52
  },
  {
    "params": {
      "category": "location",
      "slug": "gaza"
    },
    "lastUpdated": "2026-02-04T18:39:37.626Z",
    "count": 33
  },
  {
    "params": {
      "category": "location",
      "slug": "texas"
    },
    "lastUpdated": "2026-02-04T18:39:37.664Z",
    "count": 101
  },
  {
    "params": {
      "category": "location",
      "slug": "india"
    },
    "lastUpdated": "2026-02-04T18:39:37.671Z",
    "count": 102
  },
  {
    "params": {
      "category": "location",
      "slug": "china"
    },
    "lastUpdated": "2026-02-04T18:39:37.681Z",
    "count": 100
  },
  {
    "params": {
      "category": "location",
      "slug": "florida"
    },
    "lastUpdated": "2026-02-04T18:39:37.697Z",
    "count": 100
  },
  {
    "params": {
      "category": "location",
      "slug": "tokyo"
    },
    "lastUpdated": "2026-02-04T18:39:37.703Z",
    "count": 27
  }
]