[
  {
    "params": {
      "category": "location",
      "slug": "london"
    },
    "lastUpdated": "2026-03-02T12:40:12.554Z",
    "count": 103
  },
  {
    "params": {
      "category": "location",
      "slug": "texas"
    },
    "lastUpdated": "2026-03-02T12:40:12.559Z",
    "count": 101
  },
  {
    "params": {
      "category": "location",
      "slug": "china"
    },
    "lastUpdated": "2026-03-02T12:40:12.593Z",
    "count": 103
  },
  {
    "params": {
      "category": "location",
      "slug": "russia"
    },
    "lastUpdated": "2026-03-02T12:40:12.596Z",
    "count": 101
  },
  {
    "params": {
      "category": "location",
      "slug": "israel"
    },
    "lastUpdated": "2026-03-02T12:40:12.631Z",
    "count": 104
  },
  {
    "params": {
      "category": "location",
      "slug": "florida"
    },
    "lastUpdated": "2026-03-02T12:40:12.633Z",
    "count": 101
  },
  {
    "params": {
      "category": "location",
      "slug": "washington"
    },
    "lastUpdated": "2026-03-02T12:40:12.636Z",
    "count": 101
  },
  {
    "params": {
      "category": "location",
      "slug": "california"
    },
    "lastUpdated": "2026-03-02T12:40:12.668Z",
    "count": 100
  },
  {
    "params": {
      "category": "location",
      "slug": "india"
    },
    "lastUpdated": "2026-03-02T12:40:12.682Z",
    "count": 100
  },
  {
    "params": {
      "category": "location",
      "slug": "new-york"
    },
    "lastUpdated": "2026-03-02T12:40:12.698Z",
    "count": 100
  }
]