[
  {
    "params": {
      "category": "location",
      "slug": "new-york"
    },
    "lastUpdated": "2025-12-09T13:52:38.748Z",
    "count": 5
  },
  {
    "params": {
      "category": "location",
      "slug": "china"
    },
    "lastUpdated": "2025-12-09T13:52:38.750Z",
    "count": 6
  },
  {
    "params": {
      "category": "location",
      "slug": "florida"
    },
    "lastUpdated": "2025-12-09T13:52:38.753Z",
    "count": 3
  },
  {
    "params": {
      "category": "location",
      "slug": "california"
    },
    "lastUpdated": "2025-12-09T13:52:38.754Z",
    "count": 4
  }
]