[
  {
    "params": {
      "category": "people",
      "slug": "musk"
    },
    "lastUpdated": "2026-02-06T18:39:25.044Z",
    "count": 102
  },
  {
    "params": {
      "category": "people",
      "slug": "trump"
    },
    "lastUpdated": "2026-02-06T18:39:25.095Z",
    "count": 106
  },
  {
    "params": {
      "category": "people",
      "slug": "zelenskyy"
    },
    "lastUpdated": "2026-02-06T18:39:25.095Z",
    "count": 19
  },
  {
    "params": {
      "category": "people",
      "slug": "zuckerberg"
    },
    "lastUpdated": "2026-02-06T18:39:25.125Z",
    "count": 5
  }
]