[
  {
    "params": {
      "category": "people",
      "slug": "trump"
    },
    "lastUpdated": "2026-05-20T14:38:26.784Z",
    "count": 107
  },
  {
    "params": {
      "category": "people",
      "slug": "musk"
    },
    "lastUpdated": "2026-05-20T14:38:26.868Z",
    "count": 100
  },
  {
    "params": {
      "category": "people",
      "slug": "putin"
    },
    "lastUpdated": "2026-05-20T14:38:26.903Z",
    "count": 91
  },
  {
    "params": {
      "category": "people",
      "slug": "xi-jinping"
    },
    "lastUpdated": "2026-05-20T14:38:26.903Z",
    "count": 14
  }
]