[
  {
    "params": {
      "category": "people",
      "slug": "trump"
    },
    "lastUpdated": "2026-07-11T18:49:57.480Z",
    "count": 105
  },
  {
    "params": {
      "category": "people",
      "slug": "musk"
    },
    "lastUpdated": "2026-07-11T18:49:57.485Z",
    "count": 101
  },
  {
    "params": {
      "category": "people",
      "slug": "zuckerberg"
    },
    "lastUpdated": "2026-07-11T18:49:57.539Z",
    "count": 68
  },
  {
    "params": {
      "category": "people",
      "slug": "xi-jinping"
    },
    "lastUpdated": "2026-07-11T18:49:57.611Z",
    "count": 28
  }
]