[
  {
    "params": {
      "category": "people",
      "slug": "trump"
    },
    "lastUpdated": "2026-04-26T18:41:52.935Z",
    "count": 110
  },
  {
    "params": {
      "category": "people",
      "slug": "putin"
    },
    "lastUpdated": "2026-04-26T18:41:52.961Z",
    "count": 74
  },
  {
    "params": {
      "category": "people",
      "slug": "zelenskyy"
    },
    "lastUpdated": "2026-04-26T18:41:52.963Z",
    "count": 34
  },
  {
    "params": {
      "category": "people",
      "slug": "netanyahu"
    },
    "lastUpdated": "2026-04-26T18:41:52.972Z",
    "count": 18
  },
  {
    "params": {
      "category": "people",
      "slug": "musk"
    },
    "lastUpdated": "2026-04-26T18:41:52.985Z",
    "count": 100
  }
]