[
  {
    "params": {
      "category": "team",
      "slug": "dodgers"
    },
    "lastUpdated": "2026-06-13T08:52:02.163Z",
    "count": 101
  },
  {
    "params": {
      "category": "team",
      "slug": "premier-league"
    },
    "lastUpdated": "2026-06-13T08:52:02.171Z",
    "count": 101
  },
  {
    "params": {
      "category": "team",
      "slug": "nba"
    },
    "lastUpdated": "2026-06-13T08:52:02.176Z",
    "count": 102
  },
  {
    "params": {
      "category": "team",
      "slug": "nfl"
    },
    "lastUpdated": "2026-06-13T08:52:02.195Z",
    "count": 103
  },
  {
    "params": {
      "category": "team",
      "slug": "chiefs"
    },
    "lastUpdated": "2026-06-13T08:52:02.262Z",
    "count": 100
  },
  {
    "params": {
      "category": "team",
      "slug": "warriors"
    },
    "lastUpdated": "2026-06-13T08:52:02.298Z",
    "count": 100
  }
]