[
  {
    "params": {
      "category": "team",
      "slug": "nhl"
    },
    "lastUpdated": "2026-06-12T10:01:00.856Z",
    "count": 101
  },
  {
    "params": {
      "category": "team",
      "slug": "nba"
    },
    "lastUpdated": "2026-06-12T10:01:00.862Z",
    "count": 102
  },
  {
    "params": {
      "category": "team",
      "slug": "premier-league"
    },
    "lastUpdated": "2026-06-12T10:01:00.875Z",
    "count": 101
  },
  {
    "params": {
      "category": "team",
      "slug": "dodgers"
    },
    "lastUpdated": "2026-06-12T10:01:00.975Z",
    "count": 100
  },
  {
    "params": {
      "category": "team",
      "slug": "nfl"
    },
    "lastUpdated": "2026-06-12T10:01:00.980Z",
    "count": 100
  },
  {
    "params": {
      "category": "team",
      "slug": "warriors"
    },
    "lastUpdated": "2026-06-12T10:01:00.990Z",
    "count": 100
  },
  {
    "params": {
      "category": "team",
      "slug": "mlb"
    },
    "lastUpdated": "2026-06-12T10:01:00.993Z",
    "count": 100
  },
  {
    "params": {
      "category": "team",
      "slug": "lakers"
    },
    "lastUpdated": "2026-06-12T10:01:00.995Z",
    "count": 100
  },
  {
    "params": {
      "category": "team",
      "slug": "yankees"
    },
    "lastUpdated": "2026-06-12T10:01:01.001Z",
    "count": 100
  }
]