[
  {
    "params": {
      "category": "team",
      "slug": "nfl"
    },
    "lastUpdated": "2026-05-02T01:52:35.962Z",
    "count": 106
  },
  {
    "params": {
      "category": "team",
      "slug": "nba"
    },
    "lastUpdated": "2026-05-02T01:52:35.970Z",
    "count": 104
  },
  {
    "params": {
      "category": "team",
      "slug": "mlb"
    },
    "lastUpdated": "2026-05-02T01:52:35.975Z",
    "count": 101
  },
  {
    "params": {
      "category": "team",
      "slug": "nhl"
    },
    "lastUpdated": "2026-05-02T01:52:35.979Z",
    "count": 101
  },
  {
    "params": {
      "category": "team",
      "slug": "lakers"
    },
    "lastUpdated": "2026-05-02T01:52:35.983Z",
    "count": 101
  },
  {
    "params": {
      "category": "team",
      "slug": "premier-league"
    },
    "lastUpdated": "2026-05-02T01:52:36.017Z",
    "count": 102
  }
]