[
  {
    "params": {
      "category": "team",
      "slug": "nhl"
    },
    "lastUpdated": "2026-03-29T01:27:22.441Z",
    "count": 56
  },
  {
    "params": {
      "category": "team",
      "slug": "nba"
    },
    "lastUpdated": "2026-03-29T01:27:22.445Z",
    "count": 101
  },
  {
    "params": {
      "category": "team",
      "slug": "premier-league"
    },
    "lastUpdated": "2026-03-29T01:27:22.473Z",
    "count": 101
  },
  {
    "params": {
      "category": "team",
      "slug": "warriors"
    },
    "lastUpdated": "2026-03-29T01:27:22.487Z",
    "count": 101
  }
]