[
  {
    "params": {
      "category": "topics",
      "slug": "sports"
    },
    "lastUpdated": "2026-01-30T12:36:35.822Z",
    "count": 101
  },
  {
    "params": {
      "category": "topics",
      "slug": "economy"
    },
    "lastUpdated": "2026-01-30T12:36:35.827Z",
    "count": 101
  },
  {
    "params": {
      "category": "topics",
      "slug": "health"
    },
    "lastUpdated": "2026-01-30T12:36:35.843Z",
    "count": 102
  },
  {
    "params": {
      "category": "topics",
      "slug": "business"
    },
    "lastUpdated": "2026-01-30T12:36:35.847Z",
    "count": 106
  },
  {
    "params": {
      "category": "topics",
      "slug": "tech"
    },
    "lastUpdated": "2026-01-30T12:36:35.869Z",
    "count": 101
  },
  {
    "params": {
      "category": "topics",
      "slug": "world"
    },
    "lastUpdated": "2026-01-30T12:36:35.879Z",
    "count": 107
  },
  {
    "params": {
      "category": "topics",
      "slug": "politics"
    },
    "lastUpdated": "2026-01-30T12:36:35.907Z",
    "count": 101
  },
  {
    "params": {
      "category": "topics",
      "slug": "science"
    },
    "lastUpdated": "2026-01-30T12:36:35.976Z",
    "count": 52
  }
]