[
  {
    "params": {
      "category": "topics",
      "slug": "sports"
    },
    "lastUpdated": "2026-06-07T13:25:28.663Z",
    "count": 103
  },
  {
    "params": {
      "category": "topics",
      "slug": "world"
    },
    "lastUpdated": "2026-06-07T13:25:28.668Z",
    "count": 108
  },
  {
    "params": {
      "category": "topics",
      "slug": "health"
    },
    "lastUpdated": "2026-06-07T13:25:28.682Z",
    "count": 102
  },
  {
    "params": {
      "category": "topics",
      "slug": "tech"
    },
    "lastUpdated": "2026-06-07T13:25:28.697Z",
    "count": 102
  },
  {
    "params": {
      "category": "topics",
      "slug": "business"
    },
    "lastUpdated": "2026-06-07T13:25:28.703Z",
    "count": 104
  },
  {
    "params": {
      "category": "topics",
      "slug": "politics"
    },
    "lastUpdated": "2026-06-07T13:25:28.735Z",
    "count": 101
  },
  {
    "params": {
      "category": "topics",
      "slug": "science"
    },
    "lastUpdated": "2026-06-07T13:25:28.768Z",
    "count": 100
  }
]