[
  {
    "params": {
      "category": "topics",
      "slug": "world"
    },
    "lastUpdated": "2026-07-15T19:00:24.952Z",
    "count": 118
  },
  {
    "params": {
      "category": "topics",
      "slug": "sports"
    },
    "lastUpdated": "2026-07-15T19:00:24.963Z",
    "count": 104
  },
  {
    "params": {
      "category": "topics",
      "slug": "health"
    },
    "lastUpdated": "2026-07-15T19:00:25.013Z",
    "count": 102
  },
  {
    "params": {
      "category": "topics",
      "slug": "tech"
    },
    "lastUpdated": "2026-07-15T19:00:25.051Z",
    "count": 102
  },
  {
    "params": {
      "category": "topics",
      "slug": "politics"
    },
    "lastUpdated": "2026-07-15T19:00:25.076Z",
    "count": 101
  },
  {
    "params": {
      "category": "topics",
      "slug": "business"
    },
    "lastUpdated": "2026-07-15T19:00:25.089Z",
    "count": 100
  },
  {
    "params": {
      "category": "topics",
      "slug": "economy"
    },
    "lastUpdated": "2026-07-15T19:00:25.099Z",
    "count": 100
  }
]